scubagoggles/__init__.py
scubagoggles/auth.py
scubagoggles/config.py
scubagoggles/getopa.py
scubagoggles/main.py
scubagoggles/orchestrator.py
scubagoggles/policy_api.py
scubagoggles/provider.py
scubagoggles/purge.py
scubagoggles/robust_dns.py
scubagoggles/run_rego.py
scubagoggles/scuba_argument_parser.py
scubagoggles/scuba_constants.py
scubagoggles/user_setup.py
scubagoggles/utils.py
scubagoggles/version.py
scubagoggles/Testing/run_unit_tests.py
scubagoggles/Testing/Functional/conftest.py
scubagoggles/Testing/Functional/SmokeTests/README.md
scubagoggles/Testing/Functional/SmokeTests/requirements.txt
scubagoggles/Testing/Functional/SmokeTests/selenium_browser.py
scubagoggles/Testing/Functional/SmokeTests/smoke_test.py
scubagoggles/Testing/Functional/SmokeTests/smoke_test_utils.py
scubagoggles/Testing/RegoTests/calendar/calendar_api01_test.rego
scubagoggles/Testing/RegoTests/calendar/calendar_api02_test.rego
scubagoggles/Testing/RegoTests/calendar/calendar_api03_test.rego
scubagoggles/Testing/RegoTests/calendar/calendar_api04_test.rego
scubagoggles/Testing/RegoTests/chat/chat05_test.rego
scubagoggles/Testing/RegoTests/chat/chat_api01_test.rego
scubagoggles/Testing/RegoTests/chat/chat_api02_test.rego
scubagoggles/Testing/RegoTests/chat/chat_api03_test.rego
scubagoggles/Testing/RegoTests/chat/chat_api04_test.rego
scubagoggles/Testing/RegoTests/classroom/classroom_api01_test.rego
scubagoggles/Testing/RegoTests/classroom/classroom_api02_test.rego
scubagoggles/Testing/RegoTests/classroom/classroom_api03_test.rego
scubagoggles/Testing/RegoTests/classroom/classroom_api04_test.rego
scubagoggles/Testing/RegoTests/classroom/classroom_api05_test.rego
scubagoggles/Testing/RegoTests/commoncontrols/commoncontrols02_test.rego
scubagoggles/Testing/RegoTests/commoncontrols/commoncontrols03_test.rego
scubagoggles/Testing/RegoTests/commoncontrols/commoncontrols06_test.rego
scubagoggles/Testing/RegoTests/commoncontrols/commoncontrols07_test.rego
scubagoggles-0.5.0.dist-info/licenses/LICENSE
scubagoggles-0.5.0.dist-info/METADATA
scubagoggles-0.5.0.dist-info/WHEEL
scubagoggles-0.5.0.dist-info/entry_points.txt
scubagoggles-0.5.0.dist-info/top_level.txt
scubagoggles-0.5.0.dist-info/RECORD
